CHANGES.txt
LICENSE.txt
MANIFEST.in
README.rst
setup.py
djed/testing.py
djed.testing.egg-info/PKG-INFO
djed.testing.egg-info/SOURCES.txt
djed.testing.egg-info/dependency_links.txt
djed.testing.egg-info/entry_points.txt
djed.testing.egg-info/requires.txt
djed.testing.egg-info/top_level.txt